docopt-stubs/METADATA.toml
docopt-stubs/__init__.pyi
docopt-stubs/py.typed
types_docopt-0.6.11.20241107.dist-info/METADATA
types_docopt-0.6.11.20241107.dist-info/WHEEL
types_docopt-0.6.11.20241107.dist-info/top_level.txt
types_docopt-0.6.11.20241107.dist-info/RECORD
